{
  "main": {
    "id": "6e8587a449d3f912",
    "type": "split",
    "children": [
      {
        "id": "6cee7779b049bc3c",
        "type": "tabs",
        "children": [
          {
            "id": "b9b7347d1c521cd4",
            "type": "leaf",
            "state": {
              "type": "markdown",
              "state": {
                "file": "Habits/Habit Dashboard.md",
                "mode": "source",
                "source": false
              },
              "icon": "lucide-file",
              "title": "Habit Dashboard"
            }
          }
        ]
      }
    ],
    "direction": "vertical"
  },
  "left": {
    "id": "45c0268042c85649",
    "type": "split",
    "children": [
      {
        "id": "0267a7b333a2dbdc",
        "type": "tabs",
        "children": [
          {
            "id": "d6de3109bf9562dd",
            "type": "leaf",
            "state": {
              "type": "file-explorer",
              "state": {
                "sortOrder": "alphabetical",
                "autoReveal": false
              },
              "icon": "lucide-folder-closed",
              "title": "Files"
            }
          },
          {
            "id": "5a132867c9737ecb",
            "type": "leaf",
            "state": {
              "type": "search",
              "state": {
                "query": "tag:#CS",
                "matchingCase": false,
                "explainSearch": false,
                "collapseAll": false,
                "extraContext": false,
                "sortOrder": "alphabetical"
              },
              "icon": "lucide-search",
              "title": "Search"
            }
          },
          {
            "id": "fb36fb6ff0e52a16",
            "type": "leaf",
            "state": {
              "type": "bookmarks",
              "state": {},
              "icon": "lucide-bookmark",
              "title": "Bookmarks"
            }
          }
        ]
      }
    ],
    "direction": "horizontal",
    "width": 300
  },
  "right": {
    "id": "7b341addf9dc0474",
    "type": "split",
    "children": [
      {
        "id": "75b627f22497d62f",
        "type": "tabs",
        "children": [
          {
            "id": "0e6cfbff39b844ac",
            "type": "leaf",
            "state": {
              "type": "backlink",
              "state": {
                "collapseAll": false,
                "extraContext": false,
                "sortOrder": "alphabetical",
                "showSearch": false,
                "searchQuery": "",
                "backlinkCollapsed": false,
                "unlinkedCollapsed": true
              },
              "icon": "links-coming-in",
              "title": "Backlinks"
            }
          },
          {
            "id": "2af335288fcfdcaf",
            "type": "leaf",
            "state": {
              "type": "outgoing-link",
              "state": {
                "linksCollapsed": false,
                "unlinkedCollapsed": true
              },
              "icon": "links-going-out",
              "title": "Outgoing links"
            }
          },
          {
            "id": "867e3f3acc9db858",
            "type": "leaf",
            "state": {
              "type": "tag",
              "state": {
                "sortOrder": "frequency",
                "useHierarchy": true
              },
              "icon": "lucide-tags",
              "title": "Tags"
            }
          },
          {
            "id": "eb6a17394cae7974",
            "type": "leaf",
            "state": {
              "type": "outline",
              "state": {
                "file": "Bookmarks/861-my-opencode-workflow-as-a-senior-engineer-youtube.md",
                "followCursor": false,
                "showSearch": false,
                "searchQuery": ""
              },
              "icon": "lucide-list",
              "title": "Outline of 861-my-opencode-workflow-as-a-senior-engineer-youtube"
            }
          },
          {
            "id": "930f6ae5eac70332",
            "type": "leaf",
            "state": {
              "type": "git-view",
              "state": {},
              "icon": "git-pull-request",
              "title": "Source Control"
            }
          }
        ],
        "currentTab": 4
      }
    ],
    "direction": "horizontal",
    "width": 300
  },
  "left-ribbon": {
    "hiddenItems": {
      "bases:Create new base": false,
      "switcher:Open quick switcher": false,
      "graph:Open graph view": false,
      "canvas:Create new canvas": false,
      "daily-notes:Open today's daily note": false,
      "templates:Insert template": false,
      "command-palette:Open command palette": false,
      "obsidian-git:Open Git source control": false,
      "terminal:Open terminal": false,
      "macros:Add food item (search or manual entry)": false
    }
  },
  "active": "b9b7347d1c521cd4",
  "lastOpenFiles": [
    "Health/Health Dashboard.md",
    "scripts/enrich_health_frontmatter.py",
    "scripts",
    "Health/2569-06-08.md",
    "Health/2569-06-07.md",
    "Health/2569-06-06.md",
    "Health/2569-06-05.md",
    "Health/2569-06-04.md",
    "Health/2569-06-03.md",
    "Health/2569-06-02.md",
    "Health/2569-06-01.md",
    "Health/2569-05-31.md",
    "Health/2569-05-30.md",
    "Health/2569-05-29.md",
    "Health/2569-05-28.md",
    "Health/2569-05-27.md",
    "Health/2569-05-26.md",
    "Health/2569-05-25.md",
    "Health/2569-05-24.md",
    "Health/2569-05-23.md",
    "Health/2569-05-22.md",
    "Health/2569-05-21.md",
    "Health/2569-05-20.md",
    "Health/2569-05-19.md",
    "Health/2569-05-18.md",
    "Health/2569-05-17.md",
    "Health/2569-05-16.md",
    "Health/2569-05-15.md",
    "Health",
    "070 Archive/Trackers/Fitness",
    "070 Archive/Trackers/Macro Dashboards",
    "070 Archive/Trackers",
    "020 Health/Meals",
    "020 Health/Fitness",
    "020 Health/Macro Dashboards",
    "Nutrition",
    "000 Inbox/Untitled.canvas",
    "Untitled.canvas",
    "1.out.png",
    "villageout.png",
    "villagein.png",
    "u2out.png",
    "2in.png",
    "1in.png",
    "Reference/Pasted image 20240826093205.png",
    "Reference/IMG_7501.jpg",
    "Reference/Screenshot 2567-08-25 at 12.51.51.png",
    "Reference/IMG_6155.jpeg"
  ]
}